README.md
setup.py
django_global_log/__init__.py
django_global_log/admin.py
django_global_log/apps.py
django_global_log/middlewares.py
django_global_log/models.py
django_global_log/serializers.py
django_global_log/utils.py
django_global_log.egg-info/PKG-INFO
django_global_log.egg-info/SOURCES.txt
django_global_log.egg-info/dependency_links.txt
django_global_log.egg-info/requires.txt
django_global_log.egg-info/top_level.txt
django_global_log/migrations/0001_initial.py
django_global_log/migrations/0002_djangogloballog_method.py
django_global_log/migrations/0003_alter_djangogloballog_index_together.py
django_global_log/migrations/__init__.py