Metadata-Version: 2.1
Name: django-global-log
Version: 0.0.6
Summary: A Log Tool for Django
Home-page: https://www.oren.ink/
Author: Oren Zhang
Author-email: oren_zhang@outlook.com
License: UNKNOWN
Platform: UNKNOWN
